{
  "generated_at": "2026-07-08T05:28:55.961844Z",
  "regions": {
    "india": {
      "avg_score": 0.105,
      "mood": "Mixed / Neutral",
      "positive": [
        {
          "title": "RCF shares jump 3% after board approves Rs 1,500 crore FPO",
          "link": "https://economictimes.indiatimes.com/markets/stocks/news/rcf-shares-jump-3-after-board-approves-rs-1500-crore-fpo/articleshow/132254062.cms",
          "source": "Markets-Economic Times",
          "score": 0.599
        },
        {
          "title": "Trent among 5 F&amp;O stocks with a sharp rise in futures open interest",
          "link": "https://economictimes.indiatimes.com/markets/stocks/news/trent-among-5-fampo-stocks-with-a-sharp-rise-in-futures-open-interest/slideshow/132253348.cms",
          "source": "Markets-Economic Times",
          "score": 0.459
        },
        {
          "title": "Airtel to Trent: 44 stocks likely to report double-digit profit slump in Q1. Are your stocks on the list?",
          "link": "https://economictimes.indiatimes.com/markets/stocks/news/airtel-to-trent-44-stocks-likely-to-report-double-digit-profit-slump-in-q1-are-your-stocks-on-the-list/articleshow/132253779.cms",
          "source": "Markets-Economic Times",
          "score": 0.44
        },
        {
          "title": "Are bluechip stocks cheap and safe to invest in now? Radhika Gupta explains why the answer isn't so simple",
          "link": "https://economictimes.indiatimes.com/markets/stocks/news/are-bluechip-stocks-cheap-and-safe-to-invest-in-now-radhika-gupta-explains-why-the-answer-isnt-so-simple/articleshow/132253411.cms",
          "source": "Markets-Economic Times",
          "score": 0.44
        },
        {
          "title": "Info Edge shares rally 19% in 2 days after Q1 update. Here\u2019s what Nomura, Goldman Sachs, other brokerages say",
          "link": "https://economictimes.indiatimes.com/markets/stocks/news/info-edge-shares-rally-19-in-2-days-after-q1-update-heres-what-nomura-goldman-sachs-other-brokerages-say/articleshow/132253998.cms",
          "source": "Markets-Economic Times",
          "score": 0.296
        }
      ],
      "negative": [
        {
          "title": "IndiGo, HPCL, other oil sensitive stocks plunge up to 5% as US strikes on Iran lift crude prices",
          "link": "https://economictimes.indiatimes.com/markets/stocks/news/indigo-hpcl-other-oil-sensitive-stocks-plunge-up-to-5-as-us-strikes-on-iran-lifts-crude-prices/articleshow/132253542.cms",
          "source": "Markets-Economic Times",
          "score": -0.735
        },
        {
          "title": "Global Market: Samsung, SK Hynix rebound as bargain buying offsets AI chip selloff fears",
          "link": "https://economictimes.indiatimes.com/markets/us-stocks/news/global-market-samsung-sk-hynix-rebound-as-bargain-buying-offsets-ai-chip-selloff-fears/articleshow/132253789.cms",
          "source": "Markets-Economic Times",
          "score": -0.25
        }
      ],
      "sample_size": 15
    },
    "world": {
      "avg_score": 0.059,
      "mood": "Mixed / Neutral",
      "positive": [
        {
          "title": "Trump\u2019s Freedom 250 draws corporate sponsors with business before his administration",
          "link": "https://www.cnbc.com/2026/07/03/trump-freedom-250-america250-corporate-sponsors-access.html",
          "source": "Business News",
          "score": 0.637
        },
        {
          "title": "Ford achieves quality milestone, as CEO targets flawless new vehicle launches",
          "link": "https://www.cnbc.com/2026/07/03/ford-achieves-quality-milestone-targets-flawless-new-vehicle-launches.html",
          "source": "Business News",
          "score": 0.511
        },
        {
          "title": "Netflix, Disney and YouTube interested in FIFA World Cup U.S. rights; package could reach $2 billion",
          "link": "https://www.cnbc.com/2026/07/07/fifa-world-cup-media-rights-netflix-disney-youtube.html",
          "source": "Business News",
          "score": 0.421
        },
        {
          "title": "Sandwich chain Jersey Mike's files for IPO, reports 50% same-store sales growth in recent years",
          "link": "https://www.cnbc.com/2026/07/02/jersey-mikes-files-for-ipo.html",
          "source": "Business News",
          "score": 0.382
        },
        {
          "title": "Package holidays to Dubai and Egypt cheaper as European prices creep up",
          "link": "https://www.bbc.co.uk/news/articles/c17y81vnje5o?at_medium=RSS&at_campaign=rss",
          "source": "BBC News",
          "score": 0.382
        }
      ],
      "negative": [
        {
          "title": "American Express and Chase move luxury lounge wars beyond the airport",
          "link": "https://www.cnbc.com/2026/07/03/amex-chase-credit-card-lounges.html",
          "source": "Business News",
          "score": -0.557
        },
        {
          "title": "Ford Q2 sales drop 10.3% due to F-Series supplier issue, falling EV demand",
          "link": "https://www.cnbc.com/2026/07/02/ford-q2-sales.html",
          "source": "Business News",
          "score": -0.494
        },
        {
          "title": "Hundreds of jobs at risk as John Lewis plans to cut some services",
          "link": "https://www.bbc.co.uk/news/articles/c30y4vqq4p6o?at_medium=RSS&at_campaign=rss",
          "source": "BBC News",
          "score": -0.494
        },
        {
          "title": "Victims of 23andMe data breach to get $47m payout, judge rules",
          "link": "https://www.bbc.co.uk/news/articles/cn0vnx2192vo?at_medium=RSS&at_campaign=rss",
          "source": "BBC News",
          "score": -0.318
        }
      ],
      "sample_size": 20
    }
  }
}